Package/Missing_values.py
Package/__init__.py
Missing_value_3579-1.0.0.dist-info/LICENSE.txt
Missing_value_3579-1.0.0.dist-info/METADATA
Missing_value_3579-1.0.0.dist-info/WHEEL
Missing_value_3579-1.0.0.dist-info/entry_points.txt
Missing_value_3579-1.0.0.dist-info/top_level.txt
Missing_value_3579-1.0.0.dist-info/RECORD
