Metadata-Version: 2.1
Name: Missing-value-3579
Version: 1.0.0
Summary: Use this package to replace missing values in your data by mean of columns
Home-page: UNKNOWN
Author: Tanishq Chopra
Author-email: 
License: UNKNOWN
Platform: UNKNOWN
Classifier: Programming Language :: Python :: 3
Classifier: License :: OSI Approved :: MIT License
Classifier: Operating System :: OS Independent
